django_flanker/models.py
django_flanker/utils.py
django_flanker/__init__.py
django_flanker/forms.py
django_flanker/driver.py
django_flanker/validators.py
django_flanker-0.3.0.dist-info/pydist.json
django_flanker-0.3.0.dist-info/RECORD
django_flanker-0.3.0.dist-info/DESCRIPTION.rst
django_flanker-0.3.0.dist-info/METADATA
django_flanker-0.3.0.dist-info/WHEEL
django_flanker-0.3.0.dist-info/top_level.txt
