Metadata-Version: 2.0
Name: django-flanker
Version: 0.3.0
Summary: Extended EmailField validation using flanker
Home-page: https://github.com/dmpayton/django-flanker
Author: Derek Payton
Author-email: derek.payton@gmail.com
License: MIT License
Download-URL: https://github.com/dmpayton/django-flanker/tarball/v0.3.0
Keywords: django flanker mailgun email validation
Platform: UNKNOWN
Classifier: Development Status :: 4 - Beta
Classifier: Framework :: Django
Classifier: Intended Audience :: Developers
Classifier: License :: OSI Approved :: MIT License
Classifier: Natural Language :: English
Classifier: Operating System :: OS Independent
Classifier: Programming Language :: Python
Classifier: Topic :: Internet :: WWW/HTTP :: Dynamic Content
Requires-Dist: django
Requires-Dist: flanker
